materials/__about__.py
materials/__init__.py
materials/air.py
materials/argon.py
materials/boron_trioxide.py
materials/carbon_steel.py
materials/copper.py
materials/gallium_arsenide_liquid.py
materials/gallium_arsenide_solid.py
materials/graphite.py
materials/helpers.py
materials/mercury.py
materials/silicon_carbide.py
materials/silver.py
materials/water.py
materials-0.1.5.dist-info/DESCRIPTION.rst
materials-0.1.5.dist-info/METADATA
materials-0.1.5.dist-info/RECORD
materials-0.1.5.dist-info/WHEEL
materials-0.1.5.dist-info/metadata.json
materials-0.1.5.dist-info/top_level.txt
