Metadata-Version: 2.0
Name: materials
Version: 0.1.5
Summary: Density, magnetic permeability etc. for a range of materials.
Home-page: https://github.com/nschloe/materials
Author: Nico Schlömer
Author-email: nico.schloemer@gmail.com
License: License :: OSI Approved :: MIT License
Download-URL: https://github.com/nschloe/materials/releases
Platform: any
Classifier: Development Status :: 3 - Alpha
Classifier: License :: OSI Approved :: MIT License
Classifier: Intended Audience :: Science/Research
Classifier: Operating System :: OS Independent
Classifier: Programming Language :: Python
Classifier: Programming Language :: Python :: 2
Classifier: Programming Language :: Python :: 3
Classifier: Topic :: Scientific/Engineering
Classifier: Topic :: Scientific/Engineering :: Chemistry
Classifier: Topic :: Scientific/Engineering :: Physics
Requires-Dist: numpy
Requires-Dist: pipdate
